odoo/addons/pms_helpdesk_mgmt/README.rst
odoo/addons/pms_helpdesk_mgmt/__init__.py
odoo/addons/pms_helpdesk_mgmt/__manifest__.py
odoo/addons/pms_helpdesk_mgmt/controllers/__init__.py
odoo/addons/pms_helpdesk_mgmt/controllers/main.py
odoo/addons/pms_helpdesk_mgmt/controllers/myaccount.py
odoo/addons/pms_helpdesk_mgmt/demo/helpdesk_demo.xml
odoo/addons/pms_helpdesk_mgmt/models/__init__.py
odoo/addons/pms_helpdesk_mgmt/models/helpdesk_ticket.py
odoo/addons/pms_helpdesk_mgmt/security/helpdesk_security_pms.xml
odoo/addons/pms_helpdesk_mgmt/security/ir.model.access.csv
odoo/addons/pms_helpdesk_mgmt/static/description/icon.png
odoo/addons/pms_helpdesk_mgmt/static/src/js/hotel_on_company.js
odoo/addons/pms_helpdesk_mgmt/views/helpdesk_ticket_templates.xml
odoo/addons/pms_helpdesk_mgmt/views/helpdesk_ticket_views.xml
odoo14_addon_pms_helpdesk_mgmt-14.0.1.0.1.dev20.dist-info/METADATA
odoo14_addon_pms_helpdesk_mgmt-14.0.1.0.1.dev20.dist-info/WHEEL
odoo14_addon_pms_helpdesk_mgmt-14.0.1.0.1.dev20.dist-info/top_level.txt
odoo14_addon_pms_helpdesk_mgmt-14.0.1.0.1.dev20.dist-info/RECORD
