Metadata-Version: 2.1
Name: odoo14-addon-pms_helpdesk_mgmt
Version: 14.0.1.0.1.dev20
Summary: Add the option to select property in the tickets.
Home-page: https://github.com/OCA/pms
Author: Irlui Ramirez, Consultores Hoteleros Integrales, Odoo Community Association (OCA)
Author-email: support@odoo-community.org
License: AGPL-3
Classifier: Programming Language :: Python
Classifier: Framework :: Odoo
Classifier: Framework :: Odoo :: 14.0
Classifier: License :: OSI Approved :: GNU Affero General Public License v3
Requires-Python: >=3.6
Requires-Dist: odoo14-addon-helpdesk-mgmt
Requires-Dist: odoo14-addon-pms
Requires-Dist: odoo<14.1dev,>=14.0a
